smplpytorch/__init__.py
smplpytorch/demo.py
smplpytorch/display_utils.py
smplpytorch/smpl/__init__.py
smplpytorch/smpl/native/__init__.py
smplpytorch/smpl/native/webuser/__init__.py
smplpytorch/smpl/native/webuser/posemapper.py
smplpytorch/smpl/native/webuser/serialization.py
smplpytorch/smpl/pytorch/__init__.py
smplpytorch/smpl/pytorch/rodrigues_layer.py
smplpytorch/smpl/pytorch/smpl_layer.py
smplpytorch/smpl/pytorch/tensutils.py
smpl_pytorch-0.0.7.dist-info/LICENSE
smpl_pytorch-0.0.7.dist-info/METADATA
smpl_pytorch-0.0.7.dist-info/WHEEL
smpl_pytorch-0.0.7.dist-info/top_level.txt
smpl_pytorch-0.0.7.dist-info/RECORD
